[
  {
    "sign": "count:user",
    "aliases":["cu"],
    "description": "看看你说了多少话",
    "help": "/count:user 自己或at一个人",
    "usages": [
      "/count:user",
      "/count:user [*logos*]"
    ],
    "arguments": [
      {
        "name": "who",
        "require": false,
        "array": false,
        "describle": "要查看谁的，默认自己",
        "default": false
      }
    ],
    "options": [
    ]
  },
  {
    "sign": "count:bot",
    "aliases":["cb"],
    "description": "看看机器人见过多少人",
    "help": "/count:bot查看",
    "usages": [
      "/count:bot"
    ],
    "arguments": [
    ],
    "options": [
    ]
  }
]
